FrozenYoghourt/__init__.py
FrozenYoghourt/gates.py
FrozenYoghourt/maths.py
FrozenYoghourt/mode.py
FrozenYoghourt/quantum.py
FrozenYoghourt/test.py
FrozenYoghourt/circuit/__init__.py
FrozenYoghourt/gates/__init__.py
FrozenYoghourt/maths/__init__.py
FrozenYoghourt/mode/__init__.py
FrozenYoghourt/quantum/__init__.py
FrozenYoghourt/quantum/decomposition.py
FrozenYoghourt/visualization/__init__.py
FrozenYoghourt-0.0.15.11.dist-info/LICENSE.txt
FrozenYoghourt-0.0.15.11.dist-info/METADATA
FrozenYoghourt-0.0.15.11.dist-info/WHEEL
FrozenYoghourt-0.0.15.11.dist-info/top_level.txt
FrozenYoghourt-0.0.15.11.dist-info/RECORD
